repotofile/__init__.py
repotofile/cli.py
repotofile/git_operations.py
repotofile/ignored_patterns.py
repotofile/utils.py
repotofile_cli-0.2.2.dist-info/LICENSE
repotofile_cli-0.2.2.dist-info/METADATA
repotofile_cli-0.2.2.dist-info/WHEEL
repotofile_cli-0.2.2.dist-info/entry_points.txt
repotofile_cli-0.2.2.dist-info/top_level.txt
repotofile_cli-0.2.2.dist-info/RECORD
